LICENSE
MANIFEST.in
README.md
pyproject.toml
requirements.txt
setup.py
invoke_commands/__init__.py
invoke_commands/clean.py
invoke_commands/docs.py
invoke_commands/misc.py
invoke_commands/notebook_runner.py
invoke_commands/release.py
invoke_commands/sonar.py
invoke_commands/test.py
invoke_commands/vars.py
typegame/__init__.py
typegame/__main__.py
typegame/_version.py
typegame.egg-info/PKG-INFO
typegame.egg-info/SOURCES.txt
typegame.egg-info/dependency_links.txt
typegame.egg-info/requires.txt
typegame.egg-info/top_level.txt
typegame/core/__init__.py
typegame/core/app.py
typegame/core/callbacks.py
typegame/core/layout.py
typegame/core/question_class.py
typegame/core/submission_class.py
typegame/parsing/__init__.py
typegame/parsing/from_notebook.py
typegame/parsing/to_components.py