Metadata-Version: 2.1
Name: typegame
Version: 0.0.0
Summary: Educational quiz app
Home-page: https://github.com/endremborza/typegame
Author: Endre Márk Borza
License: MIT
Keywords: education;quiz;dash
Platform: any
Classifier: License :: OSI Approved :: MIT License
Requires-Python: >=3.7
